ventraip/__init__.py
ventraip/cli.py
ventraip/client.py
ventraip/dns_record.py
ventraip/domain.py
ventraip/exceptions.py
ventraip_vip_client-0.4.0.dist-info/DESCRIPTION.rst
ventraip_vip_client-0.4.0.dist-info/METADATA
ventraip_vip_client-0.4.0.dist-info/RECORD
ventraip_vip_client-0.4.0.dist-info/WHEEL
ventraip_vip_client-0.4.0.dist-info/entry_points.txt
ventraip_vip_client-0.4.0.dist-info/metadata.json
ventraip_vip_client-0.4.0.dist-info/top_level.txt
