Metadata-Version: 2.0
Name: ventraip-vip-client
Version: 0.4.0
Summary: Client to connect to and manage DNS entries registered with VentraIP
Home-page: https://github.com/cmbrad/ventraip-vip-client
Author: Christopher Bradley
Author-email: chris.bradley@cy.id.au
License: MIT
Platform: UNKNOWN
Classifier: Programming Language :: Python :: 3.6
Classifier: Development Status :: 4 - Beta
Classifier: Intended Audience :: Developers
Requires-Dist: requests (<2.19,>=2.18)
Requires-Dist: beautifulsoup4 (<4.7,>=4.6)
Requires-Dist: click (<6.8,>=6.7)
Requires-Dist: tabulate (<0.9,>=0.8)
